[
    {
        "id": 1,
        "title": "malvoro",
        "price": 450.5
    },
    {
        "id": 2,
        "title": "bienvoro",
        "price": 750.5
    },
    {
        "id": 3,
        "title": "malvoro",
        "price": 450.5
    },
    {
        "id": 4,
        "title": "malvoro",
        "price": 450.5
    },
    {
        "id": 5,
        "title": "malvoro",
        "price": 450.5
    },
    {
        "id": 6,
        "title": "malvoro",
        "price": 450.5
    },
    {
        "id": 7,
        "title": "malvoro",
        "price": 450.5
    },
    {
        "id": 8,
        "title": "malvoro",
        "price": 450.5
    },
    {
        "id": 9,
        "title": "malvoro",
        "price": 450.5
    },
    {
        "id": 10,
        "title": "malvoro",
        "price": 450.5
    },
    {
        "id": 11,
        "title": "malvoro",
        "price": 450.5
    },
    {
        "id": 12,
        "title": "malvoro",
        "price": 450.5
    },
    {
        "id": 13,
        "title": "malvoro",
        "price": 450.5
    },
    {
        "id": 14,
        "title": "malvoro",
        "price": 450.5
    },
    {
        "id": 15,
        "title": "malvoro",
        "price": 450.5
    },
    {
        "id": 16,
        "title": "malvoro",
        "price": 450.5
    },
    {
        "id": 17,
        "title": "malvoro",
        "price": 450.5
    },
    {
        "id": 18,
        "title": "malvoro",
        "price": 450.5
    },
    {
        "id": 19,
        "title": "malvoro",
        "price": 450.5
    },
    {
        "id": 20,
        "title": "malvoro",
        "price": 450.5
    },
    {
        "id": 21,
        "title": "malvoro",
        "price": 450.5
    },
    {
        "id": 22,
        "title": "malvoro",
        "price": 450.5
    },
    {
        "id": 23,
        "title": "malvoro",
        "price": 450.5
    },
    {
        "id": 24,
        "title": "malvoro",
        "price": 450.5
    },
    {
        "id": 25,
        "title": "malvoro",
        "price": 450.5
    },
    {
        "id": 26,
        "title": "malvoro",
        "price": 450.5
    },
    {
        "id": 27,
        "title": "malvoro",
        "price": 450.5
    },
    {
        "id": 28,
        "title": "malvoro",
        "price": 450.5
    },
    {
        "id": 29,
        "title": "malvoro",
        "price": 450.5
    },
    {
        "id": 30,
        "title": "malvoro",
        "price": 450.5
    },
    {
        "id": 31,
        "title": "malvoro",
        "price": 450.5
    },
    {
        "id": 32,
        "title": "malvoro",
        "price": 450.5
    },
    {
        "id": 33,
        "title": "malvoro",
        "price": 450.5
    },
    {
        "id": 34,
        "title": "malvoro",
        "price": 450.5
    },
    {
        "id": 35,
        "title": "malvoro",
        "price": 450.5
    },
    {
        "id": 36,
        "title": "malvoro",
        "price": 450.5
    },
    {
        "id": 37,
        "title": "malvoro",
        "price": 450.5
    },
    {
        "id": 38,
        "title": "malvoro",
        "price": 450.5
    },
    {
        "id": 39,
        "title": "malvoro",
        "price": 450.5
    },
    {
        "id": 40,
        "title": "malvoro",
        "price": 450.5
    },
    {
        "id": 41,
        "title": "malvoro",
        "price": 450.5
    },
    {
        "id": 42,
        "title": "malvoro",
        "price": 450.5
    },
    {
        "id": 43,
        "title": "malvoro",
        "price": 450.5
    },
    {
        "id": 44,
        "title": "malvoro",
        "price": 450.5
    },
    {
        "id": 45,
        "title": "malvoro",
        "price": 450.5
    },
    {
        "id": 46,
        "title": "malvoro",
        "price": 450.5
    },
    {
        "id": 47,
        "title": "malvoro",
        "price": 450.5
    },
    {
        "id": 48,
        "title": "malvoro",
        "price": 450.5
    },
    {
        "id": 49,
        "title": "malvoro",
        "price": 450.5
    },
    {
        "id": 50,
        "title": "malvoro",
        "price": 450.5
    },
    {
        "id": 51,
        "title": "malvoro",
        "price": 450.5
    },
    {
        "id": 52,
        "title": "malvoro",
        "price": 450.5
    },
    {
        "id": 53,
        "title": "malvoro",
        "price": 450.5
    },
    {
        "id": 54,
        "title": "malvoro",
        "price": 450.5
    },
    {
        "id": 55,
        "title": "malvoro",
        "price": 450.5
    },
    {
        "id": 56,
        "title": "malvoro",
        "price": 450.5
    },
    {
        "id": 57,
        "title": "malvoro",
        "price": 450.5
    },
    {
        "id": 58,
        "title": "malvoro",
        "price": 450.5
    },
    {
        "id": 59,
        "title": "malvoro",
        "price": 450.5
    },
    {
        "id": 60,
        "title": "malvoro",
        "price": 450.5
    },
    {
        "id": 61,
        "title": "malvoro",
        "price": 450.5
    },
    {
        "id": 62,
        "title": "malvoro",
        "price": 450.5
    },
    {
        "id": 63,
        "title": "malvoro",
        "price": 450.5
    },
    {
        "id": 64,
        "title": "malvoro",
        "price": 450.5
    },
    {
        "id": 65,
        "title": "malvoro",
        "price": 450.5
    },
    {
        "id": 66,
        "title": "malvoro",
        "price": 450.5
    },
    {
        "id": 67,
        "title": "malvoro",
        "price": 450.5
    },
    {
        "id": 68,
        "title": "malvoro",
        "price": 450.5
    },
    {
        "id": 69,
        "title": "malvoro",
        "price": 450.5
    },
    {
        "id": 70,
        "title": "malvoro",
        "price": 450.5
    },
    {
        "id": 71,
        "title": "malvoro",
        "price": 450.5
    },
    {
        "id": 72,
        "title": "malvoro",
        "price": 450.5
    },
    {
        "id": 73,
        "title": "malvoro",
        "price": 450.5
    },
    {
        "id": 74,
        "title": "malvoro",
        "price": 450.5
    },
    {
        "id": 75,
        "title": "malvoro",
        "price": 450.5
    },
    {
        "id": 76,
        "title": "malvoro",
        "price": 450.5
    },
    {
        "id": 77,
        "title": "malvoro",
        "price": 450.5
    },
    {
        "id": 78,
        "title": "malvoro",
        "price": 450.5
    },
    {
        "id": 79,
        "title": "malvoro",
        "price": 450.5
    },
    {
        "id": 80,
        "title": "malvoro",
        "price": 450.5
    },
    {
        "id": 81,
        "title": "malvoro",
        "price": 450.5
    },
    {
        "id": 82,
        "title": "malvoro",
        "price": 450.5
    },
    {
        "id": 83,
        "title": "malvoro",
        "price": 450.5
    },
    {
        "id": 84,
        "title": "malvoro",
        "price": 450.5
    },
    {
        "id": 85,
        "title": "malvoro",
        "price": 450.5
    },
    {
        "id": 86,
        "title": "malvoro",
        "price": 450.5
    },
    {
        "id": 87,
        "title": "malvoro",
        "price": 450.5
    },
    {
        "id": 88,
        "title": "malvoro",
        "price": 450.5
    },
    {
        "id": 89,
        "title": "malvoro",
        "price": 450.5
    },
    {
        "id": 90,
        "title": "malvoro",
        "price": 450.5
    },
    {
        "id": 91,
        "title": "malvoro",
        "price": 450.5
    },
    {
        "id": 92,
        "title": "malvoro",
        "price": 450.5
    },
    {
        "id": 93,
        "title": "malvoro",
        "price": 450.5
    },
    {
        "id": 94,
        "title": "malvoro",
        "price": 450.5
    },
    {
        "id": 95,
        "title": "malvoro",
        "price": 450.5
    },
    {
        "id": 96,
        "title": "malvoro",
        "price": 450.5
    },
    {
        "id": 97,
        "title": "malvoro",
        "price": 450.5
    },
    {
        "id": 98,
        "title": "malvoro",
        "price": 450.5
    },
    {
        "id": 99,
        "title": "malvoro",
        "price": 450.5
    },
    {
        "id": 100,
        "title": "malvoro",
        "price": 450.5
    },
    {
        "id": 101,
        "title": "malvoro",
        "price": 450.5
    },
    {
        "id": 102,
        "title": "malvoro",
        "price": 450.5
    },
    {
        "id": 103,
        "title": "malvoro",
        "price": 450.5
    },
    {
        "id": 104,
        "title": "malvoro",
        "price": 450.5
    },
    {
        "id": 105,
        "title": "malvoro",
        "price": 450.5
    },
    {
        "id": 106,
        "title": "malvoro",
        "price": 450.5
    },
    {
        "id": 107,
        "title": "malvoro",
        "price": 450.5
    },
    {
        "id": 108,
        "title": "malvoro",
        "price": 450.5
    },
    {
        "id": 109,
        "title": "malvoro",
        "price": 450.5
    },
    {
        "id": 110,
        "title": "malvoro",
        "price": 450.5
    },
    {
        "id": 111,
        "title": "malvoro",
        "price": 450.5
    },
    {
        "id": 112,
        "title": "malvoro",
        "price": 450.5
    },
    {
        "id": 113,
        "title": "malvoro",
        "price": 450.5
    },
    {
        "id": 114,
        "title": "malvoro",
        "price": 450.5
    },
    {
        "id": 115,
        "title": "malvoro",
        "price": 450.5
    },
    {
        "id": 116,
        "title": "malvoro",
        "price": 450.5
    },
    {
        "id": 117,
        "title": "malvoro",
        "price": 450.5
    },
    {
        "id": 118,
        "title": "malvoro",
        "price": 450.5
    },
    {
        "id": 119,
        "title": "malvoro",
        "price": 450.5
    },
    {
        "id": 120,
        "title": "malvoro",
        "price": 450.5
    },
    {
        "id": 121,
        "title": "malvoro",
        "price": 450.5
    }
]